takeme_pymsteams/__init__.py
takeme_pymsteams-1.0.0.dist-info/LICENSE
takeme_pymsteams-1.0.0.dist-info/METADATA
takeme_pymsteams-1.0.0.dist-info/WHEEL
takeme_pymsteams-1.0.0.dist-info/top_level.txt
takeme_pymsteams-1.0.0.dist-info/RECORD
