Metadata-Version: 2.1
Name: takeme-pymsteams
Version: 1.0.0
Summary: Python Wrapper for pymsteams
Home-page: https://github.com/takeme-pay/pymsteams
Author: Yukitaka Maeda
Author-email: yukitaka.maeda@takeme.com
License: GPLv3+
Keywords: pymsteams MS Teams TakeMe
Platform: any
Classifier: Programming Language :: Python
Classifier: Programming Language :: Python :: 3
Requires-Dist: pymsteams
Requires-Dist: shareplum
